python_simple_dto/__init__.py
python_simple_dto/dto.py
python_simple_dto-0.0.2.dist-info/LICENSE
python_simple_dto-0.0.2.dist-info/METADATA
python_simple_dto-0.0.2.dist-info/WHEEL
python_simple_dto-0.0.2.dist-info/top_level.txt
python_simple_dto-0.0.2.dist-info/RECORD
