Metadata-Version: 2.1
Name: python-simple-dto
Version: 0.0.2
Summary: provides DTO object for object-like experience with dicts
Home-page: https://github.com/GranderStark/python-simple-dto
Author: Lev Subbotin
Author-email: subveles@gmail.com
License: MIT
Keywords: dto,data transfer object
Platform: any
Classifier: Development Status :: 5 - Production/Stable
Classifier: Intended Audience :: Developers
Classifier: License :: OSI Approved :: MIT License
Classifier: Programming Language :: Python
Classifier: Programming Language :: Python :: 3.5
Classifier: Programming Language :: Python :: 3.6
Classifier: Programming Language :: Python :: 3.7
Classifier: Programming Language :: Python :: 3.8
Classifier: Topic :: Software Development :: Libraries :: Python Modules
Classifier: Operating System :: OS Independent
Classifier: Topic :: Text Processing
Requires-Python: >=3.5
